watchpower_api/__init__.py
watchpower_api/models.py
watchpower_api-0.3.0.dist-info/METADATA
watchpower_api-0.3.0.dist-info/WHEEL
watchpower_api-0.3.0.dist-info/RECORD
