Metadata-Version: 2.1
Name: watchpower-api
Version: 0.3.0
Summary: WatchPower Rest-API client in Python
Author: David Freire
Author-email: davidsmfreire@gmail.com
Requires-Python: >=3.9,<4.0
Classifier: Programming Language :: Python :: 3
Classifier: Programming Language :: Python :: 3.9
Classifier: Programming Language :: Python :: 3.10
Classifier: Programming Language :: Python :: 3.11
Classifier: Programming Language :: Python :: 3.12
Classifier: Programming Language :: Python :: 3.13
Requires-Dist: pydantic (>=1.0.0,<3.0.0)
Requires-Dist: requests (>=2.25.0)
